Workbook

Sheet Summary 
C1: Projwect Name : Unilock- Marengo
B4: =Sheet1!B19 -> Type of System -Ground Mount
B5: =Sheet1!B20 -> DC | C5: =Sheet1!C20 -> 1630 | D5: =Sheet1!D20 -> KWp
B6: =Sheet1!B21 -> AC | C6: =Sheet1!C21 -> 1400 | D6: =Sheet1!D21 -> KW
B7: =Sheet1!B22 -> Module Price | C7: =Sheet1!C22 -> 619400 | D7: =Sheet1!D22 -> 0.38
B8: =Sheet1!B23 -> Inverter Price | C8: =Sheet1!C23 -> 156526.41 | D8: =Sheet1!D23 -> 0.096028472
B9: =Sheet1!B24 -> Structure Price | C9: =Sheet1!C24 -> 358600 | D9: =Sheet1!D24 -> 0.22
B10: =Sheet1!B25 -> BOS | C10: =Sheet1!C25 -> 611250 | D10: =Sheet1!D25 -> 0.375
B11: =Sheet1!B26 -> Mechanical installation | C11: =Sheet1!C26 -> 391200 | D11: =Sheet1!D26 -> 0.24
B12: =Sheet1!B27 -> Electrical Installation | C12: =Sheet1!C27 -> 733500 | D12: =Sheet1!D27 -> 0.45
B13: =Sheet1!B28 -> Civil | C13: =Sheet1!C28 -> 195600 | D13: =Sheet1!D28 -> 0.12
B14: =Sheet1!B29 -> Engineering | C14: =Sheet1!C29 -> 32600 | D14: =Sheet1!D29 -> 0.02
B15: =Sheet1!B30 -> Permitting | C15: =Sheet1!C30 -> 32600 | D15: =Sheet1!D30 -> 0.02
B16: =Sheet1!B31 -> Overhead | C16: =Sheet1!C31 -> 130400 | D16: =Sheet1!D31 -> 0.08
B17: =Sheet1!B32 -> Margin | C17: =Sheet1!C32 -> 326167.64 | D17: =Sheet1!D32 -> 0.20010285
B18: =Sheet1!B34 -> Contingency Amount | C18: =Sheet1!C34 -> 107635.32 | D18: =Sheet1!D34 -> 0.06603394
B19: =Sheet1!B36 -> Total $/Wp | C19: =Sheet1!C36 -> 3695479.4 | D19: =Sheet1!D36 -> 2.2671653
B21: Note-
B22: Currently, we have used a module price of $0.38/Wp for First Solar. Please let us know if this needs to be updated.
B23: Bonding, sales and use tax is not included in the offer but can be made available upon request.
B24: Permitting costs will be determined based on actual requirements and are excluded from this cost estimate.
B25: Any cost related Utility application fees, impact studies, and utility upgrades are excluded.
B26: No cost for third Party External Study is considered
B27: The modification in the inverter location will lead to a revision of the CAPEX, as this alteration will impact the cable analysis.
B28: The cost of stamping is not covered within the design set and will incur an additional charge of $500 per set.
B29: Currently, we are considering a 10% margin on supply and installation.
B30: 3% of contingency is consdiered in the above cost
B31: Includes one mobilization and one demobilization.
B32: We have considered the cost associsted with zero-export (limiting) system.
B33: POI location is at inverter level only

Sheet Sheet1
B2: Contingency | C2: Type of System | D2: System Size | E2: Module Price | F2: Inverter Price | G2: Structure Price | H2: BOS | I2: Mechanical installation | J2: Electrical Installation | K2: Civil | L2: Engineering | M2: Permitting | N2: Overhead | O2: Margin | P2: Sales & Use Tax | Q2: Contingency Amount | R2: Bonding amount | S2: Total $/Wp
D3: =I12 -> 741.78
B4: 0.03 | C4: GM | D4: 2.2 | E4: 0.38 | F4: =N13 -> 0.096028472 | G4: 0.22 | H4: =0.375 -> 0.375 | I4: 0.24 | J4: 0.45 | K4: 0.12 | L4: 0.02 | M4: 0.02 | N4: 0.08 | O4: =SUM(E4:H4)*10%+SUM(I4:N4)*10% -> 0.20010285 | P4: 0 | Q4: =SUM(E4:O4)*B4 -> 0.06603394 | R4: 0 | S4: =SUM(E4:R4) -> 2.2671653
Q5: =SUM(E5:O5)*B5 -> 0 | S5: =S4-#REF! -> #REF!
L6: =#REF!*C9*1000 -> #REF! | M6: =#REF!*C9*1000 -> #REF!
B7: Reference from Empower NCC project | G7: =G4*C9*1000 -> 163191.6 | L7: =#REF!*C20*1000 -> #REF!
B8: Type of System -Rooftop
B9: DC | C9: 741.78 | D9: KWp | F9: DC | J9: =(#REF!+#REF!+#REF!)*C9*1000 -> #REF!
B10: AC | C10: 500 | D10: KW | F10: AC | G10: =C10+C21 -> 1900
B11: Supply | C11: =D11*$C$9*1000 -> 794467.5 | D11: =E4+F4+G4+H4 -> 1.0710285 | E11: =D11/$D$17 -> 0.47240865 | F11: Rooftop | I11: =1552*590 -> 915680
B12: Installation | C12: =D12*$C$9*1000 -> 600841.8 | D12: =I4+J4+K4 -> 0.81 | E12: =D12/$D$17 -> 0.35727435 | F12: DC | G12: 1268 | H12: 585 | I12: =H12*G12/1000 -> 741.78
B13: Engineering & permitting | C13: =D13*$C$9*1000 -> 29671.2 | D13: =L4+M4 -> 0.04 | E13: =D13/$D$17 -> 0.017643178 | F13: AC | G13: 5 | H13: 100 | I13: =H13*G13 -> 500 | J13: 10000 | K13: =J13*G13 -> 50000 | N13: =K20/I12/1000 -> 0.096028472
B14: SG&A | C14: =D14*$C$9*1000 -> 59342.4 | D14: =N4 -> 0.08 | E14: =D14/$D$17 -> 0.035286356 | G14: 0 | H14: 36 | I14: =H14*G14 -> 0 | J14: 3800 | K14: =J14*G14 -> 0
B15: Margin | C15: =D15*$C$9*1000 -> 148432.29 | D15: =O4 -> 0.20010285 | E15: =D15/$D$17 -> 0.088261253 | G15: =G12/2 -> 634 | J15: 25 | K15: =J15*G15 -> 15850
B16: Contingency | C16: =D16*$C$9*1000 -> 48982.656 | D16: =Q4 -> 0.06603394 | E16: =D16/$D$17 -> 0.029126214 | G16: 1 | J16: 857 | K16: =J16*G16 -> 857 | L16: FlexOM
B17: Total | C17: =SUM(C11:C16) -> 1681737.8 | D17: =SUM(D11:D16) -> 2.2671653 | G17: 1 | J17: 2000 | K17: =J17*G17 -> 2000 | L17: Flex Portal
G18: 1 | J18: 1750 | K18: =J18*G18 -> 1750 | L18: Onsite CPS field service ‘start-up’ commissioning support, per man day
B19: Type of System -Ground Mount | G19: =G14+G13 -> 5 | J19: 155 | K19: =J19*G19 -> 775 | L19: Shipping
B20: DC | C20: 1630 | D20: KWp | E20: =C20/C21 -> 1.1642857 | K20: =SUM(K13:K19) -> 71232 | L20: =K20/C9/1000 -> 0.096028472
B21: AC | C21: 1400 | D21: KW
B22: =E2 -> Module Price | C22: =D22*$C$20*1000 -> 619400 | D22: =E4 -> 0.38 | E22: =D22/$D$28 -> 3.1666667 | F22: DC | G22: =C20/H22*1000 -> 3260 | H22: 500 | I22: =H22*G22/1000 -> 1630
B23: =F2 -> Inverter Price | C23: =D23*$C$20*1000 -> 156526.41 | D23: =F4 -> 0.096028472 | E23: =D23/$D$28 -> 0.80023727 | F23: AC | G23: 6 | H23: 275 | I23: =H23*G23 -> 1650 | J23: =J13 -> 10000 | K23: =J23*G23 -> 60000 | L23: Inverter cost
B24: =G2 -> Structure Price | C24: =D24*$C$20*1000 -> 358600 | D24: =G4 -> 0.22 | E24: =D24/$D$28 -> 1.8333333 | G24: =G14 -> 0 | H24: 36 | I24: =H24*G24 -> 0 | J24: =J14 -> 3800 | K24: =J24*G24 -> 0 | L24: Inverter cost
B25: =H2 -> BOS | C25: =D25*$C$20*1000 -> 611250 | D25: =H4 -> 0.375 | E25: =D25/$D$28 -> 3.125 | J25: 775 | K25: =J25 -> 775 | L25: Flex OM
B26: =I2 -> Mechanical installation | C26: =D26*$C$20*1000 -> 391200 | D26: =I4 -> 0.24 | E26: =D26/$D$28 -> 2 | J26: 155 | K26: =J26*G23+G24*J26 -> 930 | L26: Shipping
B27: =J2 -> Electrical Installation | C27: =D27*$C$20*1000 -> 733500 | D27: =J4 -> 0.45 | E27: =D27/$D$28 -> 3.75 | J27: 1750 | K27: =J27 -> 1750 | L27: Onsite commissioning
B28: =K2 -> Civil | C28: =D28*$C$20*1000 -> 195600 | D28: =K4 -> 0.12 | J28: 90 | K28: =J28*(G23+G24) -> 540 | L28: Inverter roof mount leg
B29: =L2 -> Engineering | C29: =D29*$C$20*1000 -> 32600 | D29: =L4 -> 0.02 | G29: =G22/2 -> 1630 | J29: 22 | K29: =J29*G29 -> 35860 | L29: Optimiser
B30: =M2 -> Permitting | C30: =D30*$C$20*1000 -> 32600 | D30: =M4 -> 0.02 | K30: =SUM(K23:K29) -> 99855 | L30: =K30/C20/1000 -> 0.061260736
B31: =N2 -> Overhead | C31: =D31*$C$20*1000 -> 130400 | D31: =N4 -> 0.08
B32: =O2 -> Margin | C32: =D32*$C$20*1000 -> 326167.64 | D32: =O4 -> 0.20010285
B33: =P2 -> Sales & Use Tax | C33: =D33*$C$20*1000 -> 0 | D33: =P4 -> 0 | F33: Supply | G33: =1675695 -> 1675695 | H33: =5445*410 -> 2232450 | I33: =G33/$H$33 -> 0.75060808 | J33: JPMC Vision II
B34: =Q2 -> Contingency Amount | C34: =D34*$C$20*1000 -> 107635.32 | D34: =Q4 -> 0.06603394 | F34: Foundation Installation | G34: 599823.53 | H34: =G34 -> 599823.53 | I34: =G34/$H$33 -> 0.26868397
B35: =R2 -> Bonding amount | C35: =D35*$C$20*1000 -> 0 | D35: =R4 -> 0 | F35: Racking, Under Decking, | G35: 924310.59 | H35: =G35 -> 924310.59 | I35: =G35/$H$33 -> 0.41403417
B36: =S2 -> Total $/Wp | C36: =SUM(C22:C35) -> 3695479.4 | D36: =SUM(D22:D35) -> 2.2671653 | F36: Panel Installation | G36: 262588.24 | H36: =G36 -> 262588.24 | I36: =G36/$H$33 -> 0.11762335
I37: =SUM(I34:I36) -> 0.80034149
G39: for zero-export (limiting) system | H39: considering reverse power realy | I39: 50000 | J39: =I39/C20/1000 -> 0.030674847
B41: 500 | C41: 40 | D41: =C41*B41 -> 20000

Sheet Sheet3
B4: =Sheet1!E2 -> Module Price | C4: =Sheet1!F2 -> Inverter Price | D4: =Sheet1!G2 -> Structure Price | E4: =Sheet1!H2 -> BOS | F4: =Sheet1!I2 -> Mechanical installation | G4: =Sheet1!J2 -> Electrical Installation | H4: =Sheet1!K2 -> Civil | I4: =Sheet1!L2 -> Engineering | ... P4: =Sheet1!S2 -> Total $/Wp
B5: =Sheet1!E4 -> 0.38 | C5: =Sheet1!F4 -> 0.096028472 | D5: =Sheet1!G4 -> 0.22 | E5: =Sheet1!H4 -> 0.375 | F5: =Sheet1!I4 -> 0.24 | G5: =Sheet1!J4 -> 0.45 | H5: =Sheet1!K4 -> 0.12 | I5: =Sheet1!L4 -> 0.02 | ... P5: =Sheet1!S4 -> 2.2671653
C9: Installation PKG Breakdown
C10: =F4 -> Mechanical installation | D10: =F5 -> 0.24
C11: =G4 -> Electrical Installation | D11: =G5 -> 0.45
C12: =H4 -> Civil | D12: =H5 -> 0.12
C13: Total | D13: =SUM(D10:D12) -> 0.81
C15: Brakdown of Mechanical pkg
C16: =Sheet1!F34 -> Foundation Installation | D16: =Sheet1!I34 -> 0.26868397
C17: =Sheet1!F35 -> Racking, Under Decking, | D17: =Sheet1!I35 -> 0.41403417
C18: =Sheet1!F36 -> Panel Installation | D18: =Sheet1!I36 -> 0.11762335
C19: Total | D19: =SUM(D16:D18) -> 0.80034149
