Workbook

Sheet Sheet2
C1: Projwect Name : Mattingly Cold Storage
B4: =Sheet1!B20 -> Type of System -Rooftop
B5: =Sheet1!B21 -> DC | C5: =Sheet1!C21 -> 1930 | D5: =Sheet1!D21 -> KWp
B6: =Sheet1!B22 -> AC | C6: 500 | D6: =Sheet1!D22 -> KW
B7: =Sheet1!B23 -> Module Price | C7: =Sheet1!C23 -> 829900 | D7: =Sheet1!D23 -> 0.43
B8: =Sheet1!B24 -> Inverter Price | C8: =Sheet1!C24 -> 185334.95 | D8: =Sheet1!D24 -> 0.096028472
B9: =Sheet1!B25 -> Structure Price | C9: =Sheet1!C25 -> 579000 | D9: =Sheet1!D25 -> 0.3
B10: =Sheet1!B26 -> BOS | C10: =Sheet1!C26 -> 656200 | D10: =Sheet1!D26 -> 0.34
B11: =Sheet1!B27 -> Mechanical installation | C11: =Sheet1!C27 -> 482500 | D11: =Sheet1!D27 -> 0.25
B12: =Sheet1!B28 -> Electrical Installation | C12: =Sheet1!C28 -> 810600 | D12: =Sheet1!D28 -> 0.42
B13: =Sheet1!B29 -> Civil | C13: =Sheet1!C29 -> 38600 | D13: =Sheet1!D29 -> 0.02
B14: =Sheet1!B30 -> Engineering | C14: =Sheet1!C30 -> 19300 | D14: =Sheet1!D30 -> 0.01
B15: =Sheet1!B31 -> Permitting | C15: =Sheet1!C31 -> 57900 | D15: =Sheet1!D31 -> 0.03
B16: =Sheet1!B32 -> Overhead | C16: =Sheet1!C32 -> 154400 | D16: =Sheet1!D32 -> 0.08
B17: =Sheet1!B33 -> Margin | C17: =Sheet1!C33 -> 381373.5 | D17: =Sheet1!D33 -> 0.19760285
B18: =Sheet1!B35 -> Contingency Amount | C18: =Sheet1!C35 -> 209755.42 | D18: =Sheet1!D35 -> 0.10868157
B19: =Sheet1!B37 -> Total $/Wp | C19: =Sheet1!C37 -> 4404863.9 | D19: =Sheet1!D37 -> 2.2823129
B21: Note-
B22: Currently, we have used a module price of $0.43/Wp for Heline as it will be domestic content. Please let us know if this needs to be updated.
B23: Bonding, sales and use tax is not included in the offer but can be made available upon request.
B24: Permitting costs will be determined based on actual requirements and are excluded from this cost estimate.
B25: Any cost related Utility application fees, impact studies, and utility upgrades are excluded.
B26: No cost for third Party External Study is considered
B27: The modification in the inverter location will lead to a revision of the CAPEX, as this alteration will impact the cable analysis.
B28: The cost of stamping is not covered within the design set and will incur an additional charge of $500 per set.
B29: Currently, we are considering a 10% margin on supply and a 20% margin on installation.
B30: 5% of contingency is consdiered in the above cost
B31: Includes one mobilization and one demobilization.
B32: POI location is at inverter level only

Sheet Sheet1
B2: Contingency | C2: Type of System | D2: System Size | E2: Module Price | F2: Inverter Price | G2: Structure Price | H2: BOS | I2: Mechanical installation | J2: Electrical Installation | K2: Civil | L2: Engineering | M2: Permitting | N2: Overhead | O2: Margin | P2: Sales & Use Tax | Q2: Contingency Amount | R2: Bonding amount | S2: Total $/Wp
D3: =I13 -> 741.78
B4: 0.05 | C4: RT | D4: 2.2 | E4: 0.43 | F4: =N14 -> 0.096028472 | G4: 0.3 | H4: 0.34 | I4: 0.25 | J4: 0.42 | K4: 0.02 | L4: 0.01 | M4: 0.03 | N4: 0.08 | O4: =SUM(E4:H4)*10%+SUM(I4:N4)*10% -> 0.19760285 | P4: 0 | Q4: =SUM(E4:O4)*B4 -> 0.10868157 | R4: 0 | S4: =SUM(E4:R4) -> 2.2823129 | T4: =S4-E4+0.24 -> 2.0923129
B5: 0.05 | C5: RT | D5: =D4/1000 -> 0.0022 | E5: 0.22 | F5: 0.05 | G5: 0.3 | H5: 0.45 | I5: 0.25 | J5: 0.45 | K5: 0.05 | L5: 0.09 | M5: 0.05 | N5: 0.14 | O5: =SUM(E5:H5)*10%+SUM(I5:N5)*20% -> 0.308 | P5: 0 | Q5: =SUM(E5:O5)*B5 -> 0.1179 | R5: 0 | S5: =SUM(E5:R5) -> 2.4759
Q6: =SUM(E6:O6)*B6 -> 0 | S6: =S4-S5 -> -0.19358711
L7: =L5*C10*1000 -> 66760.2 | M7: =M5*C10*1000 -> 37089
B8: Reference from Empower NCC project | G8: =G4*C10*1000 -> 222534 | L8: =#REF!*C21*1000 -> #REF!
B9: Type of System -Rooftop
B10: DC | C10: 741.78 | D10: KWp | F10: DC | J10: =(I5+J5+K5)*C10*1000 -> 556335
B11: AC | C11: 500 | D11: KW | F11: AC | G11: =C11+C22 -> 2000
B12: Supply | C12: =D12*$C$10*1000 -> 864936.6 | D12: =E4+F4+G4+H4 -> 1.1660285 | E12: =D12/$D$18 -> 0.51089773 | F12: Rooftop | I12: =1552*590 -> 915680
B13: Installation | C13: =D13*$C$10*1000 -> 511828.2 | D13: =I4+J4+K4 -> 0.69 | E13: =D13/$D$18 -> 0.30232489 | F13: DC | G13: 1268 | H13: 585 | I13: =H13*G13/1000 -> 741.78
B14: Engineering & permitting | C14: =D14*$C$10*1000 -> 29671.2 | D14: =L4+M4 -> 0.04 | E14: =D14/$D$18 -> 0.017526081 | F14: AC | G14: 5 | H14: 100 | I14: =H14*G14 -> 500 | J14: 10000 | K14: =J14*G14 -> 50000 | N14: =K21/I13/1000 -> 0.096028472
B15: SG&A | C15: =D15*$C$10*1000 -> 59342.4 | D15: =N4 -> 0.08 | E15: =D15/$D$18 -> 0.035052162 | G15: 0 | H15: 36 | I15: =H15*G15 -> 0 | J15: 3800 | K15: =J15*G15 -> 0
B16: Margin | C16: =D16*$C$10*1000 -> 146577.84 | D16: =O4 -> 0.19760285 | E16: =D16/$D$18 -> 0.086580087 | G16: =G13/2 -> 634 | J16: 25 | K16: =J16*G16 -> 15850
B17: Contingency | C17: =D17*$C$10*1000 -> 80617.812 | D17: =Q4 -> 0.10868157 | E17: =D17/$D$18 -> 0.047619048 | G17: 1 | J17: 857 | K17: =J17*G17 -> 857 | L17: FlexOM
B18: Total | C18: =SUM(C12:C17) -> 1692974.1 | D18: =SUM(D12:D17) -> 2.2823129 | G18: 1 | J18: 2000 | K18: =J18*G18 -> 2000 | L18: Flex Portal
G19: 1 | J19: 1750 | K19: =J19*G19 -> 1750 | L19: Onsite CPS field service ‘start-up’ commissioning support, per man day
B20: Type of System -Rooftop | G20: =G15+G14 -> 5 | J20: 155 | K20: =J20*G20 -> 775 | L20: Shipping
B21: DC | C21: 1930 | D21: KWp | E21: =C21/C22 -> 1.2866667 | K21: =SUM(K14:K20) -> 71232 | L21: =K21/C10/1000 -> 0.096028472
B22: AC | C22: 1500 | D22: KW
B23: =E2 -> Module Price | C23: =D23*$C$21*1000 -> 829900 | D23: =E4 -> 0.43 | E23: =D23/$D$29 -> 21.5 | F23: DC | G23: =G13 -> 1268 | H23: =H13 -> 585 | I23: =H23*G23/1000 -> 741.78
B24: =F2 -> Inverter Price | C24: =D24*$C$21*1000 -> 185334.95 | D24: =F4 -> 0.096028472 | E24: =D24/$D$29 -> 4.8014236 | F24: AC | G24: 0 | H24: 60 | I24: =H24*G24 -> 0 | J24: =J14 -> 10000 | K24: =J24*G24 -> 0 | L24: Inverter cost
B25: =G2 -> Structure Price | C25: =D25*$C$21*1000 -> 579000 | D25: =G4 -> 0.3 | E25: =D25/$D$29 -> 15 | G25: =G15 -> 0 | H25: 36 | I25: =H25*G25 -> 0 | J25: =J15 -> 3800 | K25: =J25*G25 -> 0 | L25: Inverter cost
B26: =H2 -> BOS | C26: =D26*$C$21*1000 -> 656200 | D26: =H4 -> 0.34 | E26: =D26/$D$29 -> 17 | J26: 775 | K26: =J26 -> 775 | L26: Flex OM
B27: =I2 -> Mechanical installation | C27: =D27*$C$21*1000 -> 482500 | D27: =I4 -> 0.25 | E27: =D27/$D$29 -> 12.5 | J27: 155 | K27: =J27*G24+G25*J27 -> 0 | L27: Shipping
B28: =J2 -> Electrical Installation | C28: =D28*$C$21*1000 -> 810600 | D28: =J4 -> 0.42 | E28: =D28/$D$29 -> 21 | J28: 1750 | K28: =J28 -> 1750 | L28: Onsite commissioning
B29: =K2 -> Civil | C29: =D29*$C$21*1000 -> 38600 | D29: =K4 -> 0.02 | J29: 90 | K29: =J29*(G24+G25) -> 0 | L29: Inverter roof mount leg
B30: =L2 -> Engineering | C30: =D30*$C$21*1000 -> 19300 | D30: =L4 -> 0.01 | G30: =G23/2 -> 634 | J30: 22 | K30: =J30*G30 -> 13948 | L30: Optimiser
B31: =M2 -> Permitting | C31: =D31*$C$21*1000 -> 57900 | D31: =M4 -> 0.03 | K31: =SUM(K24:K30) -> 16473 | L31: =K31/C21/1000 -> 0.0085352332
B32: =N2 -> Overhead | C32: =D32*$C$21*1000 -> 154400 | D32: =N4 -> 0.08
B33: =O2 -> Margin | C33: =D33*$C$21*1000 -> 381373.5 | D33: =O4 -> 0.19760285
B34: =P2 -> Sales & Use Tax | C34: =D34*$C$21*1000 -> 0 | D34: =P4 -> 0 | F34: Supply | G34: =1675695 -> 1675695 | H34: =5445*410 -> 2232450 | I34: =G34/$H$34 -> 0.75060808 | J34: JPMC Vision II
B35: =Q2 -> Contingency Amount | C35: =D35*$C$21*1000 -> 209755.42 | D35: =Q4 -> 0.10868157 | F35: Foundation Installation | G35: 599823.53 | H35: =G35 -> 599823.53 | I35: =G35/$H$34 -> 0.26868397
B36: =R2 -> Bonding amount | C36: =D36*$C$21*1000 -> 0 | D36: =R4 -> 0 | F36: Racking, Under Decking, | G36: 924310.59 | H36: =G36 -> 924310.59 | I36: =G36/$H$34 -> 0.41403417
B37: =S2 -> Total $/Wp | C37: =SUM(C23:C36) -> 4404863.9 | D37: =SUM(D23:D36) -> 2.2823129 | F37: Panel Installation | G37: 262588.24 | H37: =G37 -> 262588.24 | I37: =G37/$H$34 -> 0.11762335
I38: =SUM(I35:I37) -> 0.80034149
B42: 500 | C42: 40 | D42: =C42*B42 -> 20000

Sheet Sheet3
B4: =Sheet1!E2 -> Module Price | C4: =Sheet1!F2 -> Inverter Price | D4: =Sheet1!G2 -> Structure Price | E4: =Sheet1!H2 -> BOS | F4: =Sheet1!I2 -> Mechanical installation | G4: =Sheet1!J2 -> Electrical Installation | H4: =Sheet1!K2 -> Civil | I4: =Sheet1!L2 -> Engineering | ... P4: =Sheet1!S2 -> Total $/Wp
B5: =Sheet1!E4 -> 0.43 | C5: =Sheet1!F4 -> 0.096028472 | D5: =Sheet1!G4 -> 0.3 | E5: =Sheet1!H4 -> 0.34 | F5: =Sheet1!I4 -> 0.25 | G5: =Sheet1!J4 -> 0.42 | H5: =Sheet1!K4 -> 0.02 | I5: =Sheet1!L4 -> 0.01 | ... P5: =Sheet1!S4 -> 2.2823129
C9: Installation PKG Breakdown
C10: =F4 -> Mechanical installation | D10: =F5 -> 0.25
C11: =G4 -> Electrical Installation | D11: =G5 -> 0.42
C12: =H4 -> Civil | D12: =H5 -> 0.02
C13: Total | D13: =SUM(D10:D12) -> 0.69
C15: Brakdown of Mechanical pkg
C16: =Sheet1!F35 -> Foundation Installation | D16: =Sheet1!I35 -> 0.26868397
C17: =Sheet1!F36 -> Racking, Under Decking, | D17: =Sheet1!I36 -> 0.41403417
C18: =Sheet1!F37 -> Panel Installation | D18: =Sheet1!I37 -> 0.11762335
C19: Total | D19: =SUM(D16:D18) -> 0.80034149
